Workbook

Sheet Задачи
A1: AURA — трекер задач маркетинга и продаж
A2: Создан 26.10.2026 по итогам созвона, обновлён 30.10.2026. Обновлять статусы еженедельно.
A4: № | B4: Блок | C4: Задача | D4: Что сделать | E4: Результат (критерий готовности) | F4: Ответственный | G4: Кто нужен / зависимость | H4: Приоритет | I4: Старт | J4: Дедлайн | K4: Статус | L4: Дней до дедлайна | M4: Комментарий
A5: 1 | B5: Организационное | C5: Отправить данные загранпаспорта и реквизиты | D5: • Скан/фото загранпаспорта • Банковские реквизиты для оплаты • Уточнить формат договора (ГПХ) и график оплаты | E5: Документы у Анастасии, формат оформления согласован | F5: Маркетолог (я) | G5: Анастасия | H5: Высокий | I5: 46321 | J5: 46322 | K5: Не начато | L5: =IF(K5="Готово","",J5-TODAY())
A6: 2 | B6: Организационное | C6: Таск-трекер в Excel | D6: • Зафиксировать задачи по итогам созвона • Проставить ответственных, дедлайны, статусы • Обновлять статусы еженедельно (пятница) | E6: Трекер отправлен команде и обновляется раз в неделю | F6: Маркетолог (я) | G6: — | H6: Высокий | I6: 46321 | J6: 46321 | K6: Готово | L6: =IF(K6="Готово","",J6-TODAY())
A7: 3 | B7: Организационное | C7: Создать базу знаний в Notion | D7: • Структура: компания и команда, услуги и прайс, Hemaya и лицензии, сегменты и конкуренты, маркетинг и контент, продажи (воронка, скрипты, шаблоны КП), онбординг новых сотрудников • Перенести готовые материалы (выжимки по конкурентам, сегментам, Hemaya, LinkedIn, SEO-аудит, сравнение CRM) • Выдать доступы команде, договориться, кто что обновляет | E7: База знаний в Notion, команда пользуется; новый сейл и инженер онбордятся по ней | F7: Маркетолог (я) | G7: Анастасия (рабочий аккаунт), вся команда — доступ | H7: Средний | I7: 46325 | J7: 46339 | K7: Не начато | L7: =IF(K7="Готово","",J7-TODAY())
A8: 4 | B8: Организационное | C8: Спецодежда для инженеров и монтажников | D8: • Уточнить объём задачи: для кого (инженер с 9.11, монтажники), сколько комплектов и что входит (футболки/поло, брюки, кепки, жилеты) • Требования: лёгкая ткань под жару, светоотражающие элементы для объектов, логотип AURA и контакты • Макет брендирования • Запросить 2–3 предложения у поставщиков в ОАЭ (цена, сроки) • Согласовать и заказать | E8: Спецодежда заказана, к выходу монтажников команда в брендированной форме | F8: Маркетолог (я) | G8: Антон (бюджет, согласование), Игнат (кол-во и размеры) | H8: Средний | I8: 46325 | J8: 46335 | K8: Не начато | L8: =IF(K8="Готово","",J8-TODAY())
A9: 5 | B9: Доступы | C9: Доступ к сайту | D9: • Админка / CMS или репозиторий сайта (Next.js) • Хостинг и домен — кто владелец • Google Analytics 4 и Google Search Console • Кто вносит правки: я или Роман | E9: Есть рабочие доступы, понятен порядок внесения правок | F9: Маркетолог (я) | G9: Анастасия, Роман | H9: Высокий | I9: 46321 | J9: 46323 | K9: Не начато | L9: =IF(K9="Готово","",J9-TODAY())
A10: 6 | B10: Доступы | C10: Рабочий Google-аккаунт | D10: • Получить рабочий аккаунт (почта на домене или общий) • Доступ к общему Google Drive с материалами • Подключить к GA4, Search Console, будущему Google Business Profile | E10: Работаю из рабочего аккаунта, все материалы в общей папке | F10: Маркетолог (я) | G10: Анастасия / Антон | H10: Высокий | I10: 46321 | J10: 46323 | K10: Не начато | L10: =IF(K10="Готово","",J10-TODAY())
A11: 7 | B11: Доступы | C11: Доступ к Facebook-странице и LinkedIn | D11: • Роль администратора/редактора страницы Facebook • Доступ к Meta Business Suite • Доступ к странице компании в LinkedIn (если есть) и к профилю Антона для публикаций — по согласованию | E11: Могу публиковать и смотреть статистику в FB и LinkedIn | F11: Маркетолог (я) | G11: Анастасия, Антон, Роман | H11: Высокий | I11: 46321 | J11: 46324 | K11: Не начато | L11: =IF(K11="Готово","",J11-TODAY())
A12: 8 | B12: Контент | C12: Получить актуальный контент-план | D12: • Забрать у Романа текущий контент-план и статус постов (что опубликовано, что в работе) • Свести с имеющимися материалами: 8 готовых постов RU/EN, 30 идей, сценарии видео Антона • Определить каналы и частоту | E12: Единый контент-план с датами публикаций на ноябрь | F12: Маркетолог (я) | G12: Роман, Анастасия | H12: Высокий | I12: 46321 | J12: 46325 | K12: Не начато | L12: =IF(K12="Готово","",J12-TODAY())
A13: 9 | B13: Презентации | C13: Собрать текущие презентации и материалы | D13: • Получить от Романа все презентации, листовки, sales kit с пакетами цен • Зафиксировать, какие презентации в работе и для кого | E13: Все материалы в общей папке, понятен статус каждой презентации | F13: Маркетолог (я) | G13: Роман, Анастасия | H13: Высокий | I13: 46321 | J13: 46323 | K13: Не начато | L13: =IF(K13="Готово","",J13-TODAY())
A14: 10 | B14: Презентации | C14: Определить список презентаций и ТЗ к ним | D14: • Согласовать с Антоном, какие презентации нужны в первую очередь (напр. общая B2B, B2C для вилл, AMC/сервис) • Для каждой: аудитория, цель, структура, что показываем (лицензии, процесс, оборудование, цены) | E14: Утверждённый список презентаций с ТЗ и приоритетом | F14: Маркетолог (я) | G14: Антон | H14: Высокий | I14: 46323 | J14: 46325 | K14: Не начато | L14: =IF(K14="Готово","",J14-TODAY())
A15: 11 | B15: Презентации | C15: Подготовить презентацию №1 (приоритетная) | D15: • Структура и тексты (EN, при необходимости RU) • Дизайн в стиле сайта/бренда • Согласование с Антоном, правки | E15: Финальная версия PDF + редактируемый исходник | F15: Маркетолог (я) | G15: Антон (согласование), Роман (дизайн — при необходимости) | H15: Высокий | I15: 46325 | J15: 46331 | K15: Не начато | L15: =IF(K15="Готово","",J15-TODAY())
A16: 12 | B16: Презентации | C16: Подготовить презентацию №2 | D16: • По тому же процессу, что №1 | E16: Финальная версия PDF + исходник | F16: Маркетолог (я) | G16: Антон | H16: Средний | I16: 46331 | J16: 46338 | K16: Не начато | L16: =IF(K16="Готово","",J16-TODAY())
... A26: 22 | B26: Лидогенерация | C26: Запуск лидогенерации | D26: • Старт публикаций и аутрича по плану • Еженедельный отчёт: лиды, источники, конверсия | E26: Первые лиды в CRM, еженедельный отчёт | F26: Маркетолог (я) | G26: Сейл (если нанят), Антон | H26: Высокий | I26: 46342 | J26: 46356 | K26: Не начато | L26: =IF(K26="Готово","",J26-TODAY())

Sheet Сводка
A1: Сводка по статусам
A3: Статус | B3: Задач
A4: Не начато | B4: =COUNTIF(Задачи!$K$5:$K$26,A4)
A5: В работе | B5: =COUNTIF(Задачи!$K$5:$K$26,A5)
A6: На согласовании | B6: =COUNTIF(Задачи!$K$5:$K$26,A6)
A7: Ждёт доступа | B7: =COUNTIF(Задачи!$K$5:$K$26,A7)
A8: Готово | B8: =COUNTIF(Задачи!$K$5:$K$26,A8)
A9: Отменено | B9: =COUNTIF(Задачи!$K$5:$K$26,A9)
A10: Всего | B10: =COUNTA(Задачи!$C$5:$C$26)
A11: Просрочено | B11: =COUNTIFS(Задачи!$J$5:$J$26,"<"&TODAY(),Задачи!$K$5:$K$26,"<>Готово",Задачи!$K$5:$K$26,"<>Отменено")
A13: Ключевые вехи
A14: 28.10 | B14: Все доступы получены (сайт, Google, FB/LinkedIn)
A15: 31.10 | B15: Критерии сейла и требования к CRM готовы
A16: 05.11 | B16: Презентация №1 готова
A17: 06–07.11 | B17: Воронка B2B/B2C и стратегия LinkedIn
A18: 07.11 | B18: Профиль в Google Maps создан и отправлен на верификацию
A19: 09.11 | B19: Спецодежда заказана
A20: 13.11 | B20: CRM настроена, база знаний в Notion готова
A21: 16–30.11 | B21: Запуск лидогенерации
